beproduct/__init__.py
beproduct/_automation.py
beproduct/_block.py
beproduct/_color.py
beproduct/_common_apps.py
beproduct/_common_attributes.py
beproduct/_common_comments.py
beproduct/_common_revisions.py
beproduct/_common_share.py
beproduct/_common_tags.py
beproduct/_common_upload.py
beproduct/_directory.py
beproduct/_encoder.py
beproduct/_exception.py
beproduct/_helpers.py
beproduct/_image.py
beproduct/_material.py
beproduct/_raw_api.py
beproduct/_raw_api_async.py
beproduct/_schema.py
beproduct/_style.py
beproduct/_tracking.py
beproduct/_user.py
beproduct/auth.py
beproduct/sdk.py
beproduct/helpers/__init__.py
beproduct/helpers/composable.py
beproduct/helpers/impersonation.py
beproduct/helpers/parsers.py
beproduct-0.6.29.dist-info/licenses/LICENSE
beproduct-0.6.29.dist-info/METADATA
beproduct-0.6.29.dist-info/WHEEL
beproduct-0.6.29.dist-info/top_level.txt
beproduct-0.6.29.dist-info/RECORD
