Metadata-Version: 2.4
Name: beproduct
Version: 0.6.29
Summary: BeProduct Public API SDK
Home-page: https://github.com/BeProduct/BeProduct.Python.SDK
Author: Yuri Golub
Author-email: support@beproduct.com
Project-URL: Bug Tracker, https://github.com/BeProduct/BeProduct.Python.SDK/issues
Classifier: Programming Language :: Python :: 3
Classifier: License :: OSI Approved :: MIT License
Classifier: Operating System :: OS Independent
Requires-Python: >=3.10
License-File: LICENSE
Requires-Dist: requests
Requires-Dist: aiohttp
Dynamic: license-file
